applied/__init__.py
applied/client.py
applied/error.py
applied/utils.py
applied/backend/__init__.py
applied/backend/base.py
applied/backend/redis.py
applied/backend/utils.py
applied/interface/__init__.py
applied/interface/appstoreconnect.py
applied/interface/base.py
applied/interface/portal.py
applied/models/__init__.py
applied/models/api_key.py
applied/models/app.py
applied/models/base.py
applied/models/bundle.py
applied/models/capability.py
applied/models/certificate.py
applied/models/device.py
applied/models/profile.py
applied/models/provider.py
applied/models/queryset.py
applied/models/user.py
applied-0.0.2.post2.dist-info/LICENSE
applied-0.0.2.post2.dist-info/METADATA
applied-0.0.2.post2.dist-info/WHEEL
applied-0.0.2.post2.dist-info/top_level.txt
applied-0.0.2.post2.dist-info/RECORD
